[
  {"name": "kick-first-8", "x": 200, "y": 0, "width": 200, "height": 200},
  {"name": "kick-first-9", "x": 400, "y": 0, "width": 200, "height": 200},
  {"name": "kick-first-10", "x": 600, "y": 0, "width": 200, "height": 200},
  {"name": "kick-first-11", "x": 800, "y": 0, "width": 200, "height": 200},
  {"name": "kick-second-1", "x": 0, "y": 200, "width": 200, "height": 200},
  {"name": "kick-second-2", "x": 200, "y": 200, "width": 200, "height": 200},
  {"name": "kick-second-3", "x": 400, "y": 200, "width": 200, "height": 200},
  {"name": "kick-second-4", "x": 600, "y": 200, "width": 200, "height": 200},
  {"name": "kick-second-5", "x": 800, "y": 200, "width": 200, "height": 200},
  {"name": "kick-second-6", "x": 0, "y": 400, "width": 200, "height": 200},
  {"name": "kick-second-7", "x": 200, "y": 400, "width": 200, "height": 200},
  {"name": "kick-second-8", "x": 400, "y": 400, "width": 200, "height": 200},
  {"name": "kick-second-9", "x": 600, "y": 400, "width": 200, "height": 200},
  {"name": "kick-second-10", "x": 800, "y": 400, "width": 200, "height": 200},
  {"name": "kick-second-11", "x": 0, "y": 600, "width": 200, "height": 200},
  {"name": "kick-first-1", "x": 200, "y": 600, "width": 200, "height": 200},
  {"name": "kick-first-2", "x": 400, "y": 600, "width": 200, "height": 200},
  {"name": "kick-first-3", "x": 600, "y": 600, "width": 200, "height": 200},
  {"name": "kick-first-4", "x": 800, "y": 600, "width": 200, "height": 200},
  {"name": "kick-first-5", "x": 0, "y": 800, "width": 200, "height": 200},
  {"name": "kick-first-6", "x": 200, "y": 800, "width": 200, "height": 200},
  {"name": "kick-first-7", "x": 400, "y": 800, "width": 200, "height": 200}
]